timescaleutils/__init__.py
timescaleutils/logger.py
timescaleutils/main.py
timescaleutils/timescale.py
timescaleutils/constants/__init__.py
timescaleutils/constants/app_conf.py
timescaleutils/constants/datatypes.py
timescaleutils-0.2.1.dist-info/LICENSE
timescaleutils-0.2.1.dist-info/METADATA
timescaleutils-0.2.1.dist-info/WHEEL
timescaleutils-0.2.1.dist-info/top_level.txt
timescaleutils-0.2.1.dist-info/RECORD
