Metadata-Version: 2.1
Name: timescaleutils
Version: 0.2.1
Summary: Utility for TimescaleDB
Author: Knowledge Lens
Author-email: kayef.ahamad@knowledgelens.com
License: BSD 2-clause
Classifier: Development Status :: 1 - Planning
Classifier: Intended Audience :: Science/Research
Classifier: License :: OSI Approved :: BSD License
Classifier: Operating System :: POSIX :: Linux
Classifier: Programming Language :: Python :: 2
Classifier: Programming Language :: Python :: 2.7
Classifier: Programming Language :: Python :: 3
Classifier: Programming Language :: Python :: 3.4
Classifier: Programming Language :: Python :: 3.5
License-File: LICENSE
Requires-Dist: pytz
Requires-Dist: sqlalchemy
Requires-Dist: setuptools
